concrete_autoencoder/__init__.py
concrete_autoencoder-0.0.1.dist-info/LICENSE
concrete_autoencoder-0.0.1.dist-info/METADATA
concrete_autoencoder-0.0.1.dist-info/WHEEL
concrete_autoencoder-0.0.1.dist-info/top_level.txt
concrete_autoencoder-0.0.1.dist-info/RECORD
