Metadata-Version: 2.1
Name: concrete-autoencoder
Version: 0.0.1
Summary: An implementation of Concrete Autoencoders
Home-page: https://github.com/mfbalin/Concrete-Autoencoders
Author: Muhammed Fatih Balin
Author-email: m.f.balin@gmail.com
License: UNKNOWN
Platform: UNKNOWN
Classifier: Programming Language :: Python :: 3
Classifier: License :: OSI Approved :: MIT License
Classifier: Operating System :: OS Independent
Requires-Python: >=3
